MANIFEST.in
README.rst
setup.cfg
setup.py
docs/CREDITS.txt
docs/HISTORY.txt
docs/INSTALL.txt
docs/LICENSE.GPL
docs/LICENSE.txt
src/__init__.py
src/collective/__init__.py
src/collective.twitter.accounts.egg-info/PKG-INFO
src/collective.twitter.accounts.egg-info/SOURCES.txt
src/collective.twitter.accounts.egg-info/dependency_links.txt
src/collective.twitter.accounts.egg-info/entry_points.txt
src/collective.twitter.accounts.egg-info/namespace_packages.txt
src/collective.twitter.accounts.egg-info/not-zip-safe
src/collective.twitter.accounts.egg-info/requires.txt
src/collective.twitter.accounts.egg-info/top_level.txt
src/collective/twitter/__init__.py
src/collective/twitter/accounts/__init__.py
src/collective/twitter/accounts/config.py
src/collective/twitter/accounts/configure.zcml
src/collective/twitter/accounts/testing.py
src/collective/twitter/accounts/Extensions/Install.py
src/collective/twitter/accounts/Extensions/__init__.py
src/collective/twitter/accounts/browser/__init__.py
src/collective/twitter/accounts/browser/configure.zcml
src/collective/twitter/accounts/browser/controlpanel.py
src/collective/twitter/accounts/browser/interfaces.py
src/collective/twitter/accounts/browser/token.py
src/collective/twitter/accounts/browser/css/twitter.css
src/collective/twitter/accounts/browser/icons/remove.png
src/collective/twitter/accounts/browser/icons/twitter.png
src/collective/twitter/accounts/browser/js/twitter.js
src/collective/twitter/accounts/browser/templates/twitter-control-panel.pt
src/collective/twitter/accounts/locales/collective.twitter.accounts.pot
src/collective/twitter/accounts/locales/es/LC_MESSAGES/collective.twitter.accounts.po
src/collective/twitter/accounts/profiles/default/controlpanel.xml
src/collective/twitter/accounts/profiles/default/metadata.xml
src/collective/twitter/accounts/profiles/initial/metadata.xml
src/collective/twitter/accounts/profiles/initial/registry.xml
src/collective/twitter/accounts/profiles/uninstall/controlpanel.xml
src/collective/twitter/accounts/profiles/uninstall/registry.xml
src/collective/twitter/accounts/tests/__init__.py
src/collective/twitter/accounts/tests/test_controlpanel.py
src/collective/twitter/accounts/tests/test_setup.py