Metadata-Version: 1.0
Name: collective.twitter.accounts
Version: 1.0.3
Summary: Provide Twitter integration for a Plone Site
Home-page: https://github.com/collective/collective.twitter.accounts
Author: Franco Pellegrini
Author-email: frapell@gmail.com
License: GPL
Platform: UNKNOWN
Classifier: Development Status :: 5 - Production/Stable
Classifier: Environment :: Web Environment
Classifier: Framework :: Plone
Classifier: Framework :: Plone :: 4.1
Classifier: Intended Audience :: System Administrators
Classifier: License :: OSI Approved :: GNU General Public License (GPL)
Classifier: Operating System :: OS Independent
Classifier: Programming Language :: JavaScript
Classifier: Programming Language :: Python
Classifier: Programming Language :: Python :: 2.6
Classifier: Topic :: Software Development :: Libraries :: Python Modules
